nbdev_plotly/__init__.py
nbdev_plotly/_modidx.py
nbdev_plotly/plotly.py
nbdev_plotly-0.0.16.dist-info/LICENSE
nbdev_plotly-0.0.16.dist-info/METADATA
nbdev_plotly-0.0.16.dist-info/WHEEL
nbdev_plotly-0.0.16.dist-info/entry_points.txt
nbdev_plotly-0.0.16.dist-info/top_level.txt
nbdev_plotly-0.0.16.dist-info/RECORD
