Metadata-Version: 2.1
Name: nbdev-plotly
Version: 0.0.16
Summary: proc to convert plotly to widget json for quatro processing
Home-page: https://github.com/sudhanshu2340/nbdev-plotly
Author: Sudhanshu
Author-email: sudhanshu2340@gmail.com
License: Apache Software License 2.0
Keywords: nbdev jupyter notebook python
Classifier: Development Status :: 4 - Beta
Classifier: Intended Audience :: Developers
Classifier: Natural Language :: English
Classifier: Programming Language :: Python :: 3.7
Classifier: Programming Language :: Python :: 3.8
Classifier: Programming Language :: Python :: 3.9
Classifier: Programming Language :: Python :: 3.10
Classifier: License :: OSI Approved :: Apache Software License
Requires-Python: >=3.7
License-File: LICENSE
Provides-Extra: dev
